adrt/__init__.py
adrt/_adrt_cdefs.pyd
adrt/_adrt_cdefs.pyi
adrt/_wrappers.py
adrt/core.py
adrt/py.typed
adrt/utils.py
adrt-1.2.0.dist-info/licenses/LICENSE.txt
adrt-1.2.0.dist-info/METADATA
adrt-1.2.0.dist-info/WHEEL
adrt-1.2.0.dist-info/top_level.txt
adrt-1.2.0.dist-info/RECORD
