Metadata-Version: 2.4
Name: adrt
Version: 1.2.0
Summary: Fast approximate discrete Radon transform for NumPy arrays
Author: Karl Otness, Donsub Rim
License-Expression: BSD-3-Clause
Project-URL: Homepage, https://github.com/karlotness/adrt
Project-URL: Documentation, https://adrt.readthedocs.io
Project-URL: Source Code, https://github.com/karlotness/adrt
Project-URL: Bug Tracker, https://github.com/karlotness/adrt/issues
Classifier: Development Status :: 5 - Production/Stable
Classifier: Intended Audience :: Science/Research
Classifier: Topic :: Scientific/Engineering
Classifier: Topic :: Scientific/Engineering :: Image Processing
Classifier: Programming Language :: Python :: 3
Classifier: Programming Language :: Python :: 3.10
Classifier: Programming Language :: Python :: 3.11
Classifier: Programming Language :: Python :: 3.12
Classifier: Programming Language :: Python :: 3.13
Classifier: Programming Language :: Python :: 3 :: Only
Classifier: Programming Language :: Python :: Implementation :: CPython
Classifier: Programming Language :: Python :: Free Threading :: 2 - Beta
Classifier: Programming Language :: C++
Classifier: Operating System :: POSIX :: Linux
Classifier: Operating System :: Microsoft :: Windows
Classifier: Operating System :: MacOS
Classifier: Typing :: Typed
Requires-Python: >=3.10
License-File: LICENSE.txt
Requires-Dist: numpy<3,>=1.23
Dynamic: license-file
